repr_utils/__init__.py
repr_utils/_base.py
repr_utils/_jinja.py
repr_utils/_util.py
repr_utils/header.py
repr_utils/link.py
repr_utils/list.py
repr_utils/table.py
repr_utils/templates/__init__.py
repr_utils/templates/table_html.jinja
repr_utils-0.2.1.dist-info/WHEEL
repr_utils-0.2.1.dist-info/METADATA
repr_utils-0.2.1.dist-info/RECORD
